{"name":"Albacore","slug":"albacore","version":"1.0.0","preview_url":"https://wp-themes.com/albacore/","author":"wowsthemes","screenshot_url":"//ts.w.org/wp-content/themes/albacore/screenshot.png?ver=1.0.0","rating":100,"num_ratings":1,"downloaded":2244,"last_updated":"2022-10-07","last_updated_time":"2022-10-07 04:26:46","homepage":"https://wordpress.org/themes/albacore/","sections":{"description":"Albacore is a block based Wwwows WordPress theme with full site editing features. Check the theme demos at wwwows.com. Albacore has a modern, trendy style and design for portfolio, business or any other content. The theme is multipurpose, so if You like the style, You can use it to represent Your art, business, an event, show Your portfolio, start a blog, start a webshop and sell Your products etc. The theme is responsive so looks good on almost every devices. You can setup multiple header styles, navigation styles and layouts. The demo on the theme page uses the Albacore Premium child theme also. The premium version has extra features for WooCommerce, unique blocks, effects, additional and full page templates etc. You can find a documentation with an install guide and a tutorials at wwwows.com/docs."},"download_link":"https://downloads.wordpress.org/theme/albacore.1.0.0.zip","tags":{"block-patterns":"Block Editor Patterns","blog":"Blog","custom-background":"Custom Background","custom-colors":"Custom Colors","custom-logo":"Custom Logo","custom-menu":"Custom Menu","e-commerce":"E-Commerce","editor-style":"Editor Style","featured-images":"Featured Images","full-site-editing":"Full Site Editing","one-column":"One Column","portfolio":"Portfolio","rtl-language-support":"RTL Language Support","theme-options":"Theme Options","threaded-comments":"Threaded Comments","translation-ready":"Translation Ready","wide-blocks":"Wide Blocks"}}