[{"title":"Auto Car Dealership","html":"<!-- wp:template-part {\"slug\":\"header\",\"tagName\":\"header\"} /-->\n<!-- wp:group {\"align\":\"full\"} -->\n<div class=\"wp-block-group alignfull\">\n\t<!-- wp:cover {\"url\":\"http://raw.githubusercontent.com/ellatrix/block-themes-directory/main/themes/auto-car-dealership/images/hero-banner.png\",\"id\":2543,\"dimRatio\":90,\"focalPoint\":{\"x\":\"0.86\",\"y\":\"0.16\"},\"minHeight\":300,\"customGradient\":\"linear-gradient(90deg,rgb(0,0,0) 30%,rgba(150,149,240,0) 96%)\",\"className\":\"innerpage-banner\"} -->\n<div class=\"wp-block-cover innerpage-banner\" style=\"min-height:300px\"><span aria-hidden=\"true\" class=\"wp-block-cover__background has-background-dim-90 has-background-dim wp-block-cover__gradient-background has-background-gradient\" style=\"background:linear-gradient(90deg,rgb(0,0,0) 30%,rgba(150,149,240,0) 96%)\"></span><img class=\"wp-block-cover__image-background wp-image-2543\" alt=\"\" src=\"http://raw.githubusercontent.com/ellatrix/block-themes-directory/main/themes/auto-car-dealership/images/hero-banner.png\" style=\"object-position:86% 16%\" data-object-fit=\"cover\" data-object-position=\"86% 16%\"/><div class=\"wp-block-cover__inner-container\"><!-- wp:group {\"align\":\"wide\",\"layout\":{\"inherit\":true}} -->\n<div class=\"wp-block-group alignwide\"><!-- wp:post-title {\"textAlign\":\"center\",\"level\":1,\"align\":\"wide\",\"style\":{\"typography\":{\"fontSize\":\"35px\",\"fontStyle\":\"normal\",\"fontWeight\":\"700\",\"textTransform\":\"uppercase\"}},\"textColor\":\"foreground\"} /--></div>\n<!-- /wp:group -->\n\n<!-- wp:image {\"id\":1860,\"sizeSlug\":\"full\",\"linkDestination\":\"none\",\"className\":\"title-img\"} -->\n<figure class=\"wp-block-image size-full title-img\"><img src=\"http://raw.githubusercontent.com/ellatrix/block-themes-directory/main/themes/auto-car-dealership/images/car-border1.png\" alt=\"\" class=\"wp-image-1860\"/></figure>\n<!-- /wp:image --></div></div>\n<!-- /wp:cover -->\nWarning: Trying to access array offset on value of type int in /Applications/MAMP/htdocs/block-based-themes/pattern.php on line 15\n\n\t<!-- wp:group {\"tagName\":\"main\",\"align\":\"full\",\"style\":{\"spacing\":{\"padding\":{\"top\":\"80px\",\"bottom\":\"80px\",\"left\":\"100px\",\"right\":\"100px\"}}},\"layout\":{\"inherit\":true}} -->\n\t<main\n\t\tclass=\"wp-block-group alignfull\"\n\t\tstyle=\"\n\t\t\tpadding-top: 80px;\n\t\t\tpadding-right: 100px;\n\t\t\tpadding-bottom: 80px;\n\t\t\tpadding-left: 100px;\n\t\t\"\n\t>\n\t\t<!-- wp:columns {\"align\":\"wide\",\"style\":{\"spacing\":{\"padding\":{\"right\":\"0px\",\"left\":\"0px\"}}}} -->\n\t\t<div class=\"wp-block-columns alignwide\" style=\"padding-right: 0px; padding-left: 0px\">\n\t\t\t<!-- wp:column {\"width\":\"25%\"} -->\n\t\t\t\t<div class=\"wp-block-column\" style=\"flex-basis: 25%\">\n\t\t\t\t\t<!-- wp:template-part {\"slug\":\"sidebar\",\"theme\":\"auto-car-dealership\",\"tagName\":\"div\"} /-->\n\t\t\t\t</div>\n\t\t\t<!-- /wp:column -->\n\n\t\t\t<!-- wp:column {\"width\":\"75%\",\"style\":{\"spacing\":{\"padding\":{\"top\":\"0px\",\"right\":\"0px\",\"bottom\":\"0px\",\"left\":\"0px\"}}}} -->\n\t\t\t<div class=\"wp-block-column\"\n\t\t\t\tstyle=\"\n\t\t\t\t\tpadding-top: 0px;\n\t\t\t\t\tpadding-right: 0px;\n\t\t\t\t\tpadding-bottom: 0px;\n\t\t\t\t\tpadding-left: 0px;\n\t\t\t\t\tflex-basis: 75%;\n\t\t\t\t\">\n\t\t\t\t<!-- wp:group -->\n\t\t\t\t\t<div class=\"wp-block-group\"><!-- wp:latest-posts {\"postsToShow\":18,\"displayPostContent\":true,\"excerptLength\":22,\"displayPostDate\":true,\"postLayout\":\"grid\",\"displayFeaturedImage\":true} /--></div>\n\t\t\t\t<!-- /wp:group -->\n\t\t\t</div>\n\t\t\t<!-- /wp:column -->\n\t\t</div>\n\t\t<!-- /wp:columns -->\n\t</main>\n\t<!-- /wp:group -->\n</div>\n<!-- /wp:group -->\n<!-- wp:template-part {\"slug\":\"footer\",\"tagName\":\"footer\"} /-->\n"},{"title":"ArtsyLens","html":"<!-- wp:template-part {\"slug\":\"header\",\"tagName\":\"header\"} /-->\n<!-- wp:group {\"align\":\"full\",\"className\":\"banner-without-bg\",\"layout\":{\"inherit\":false}} -->\n<div class=\"wp-block-group alignfull banner-without-bg\"><!-- wp:group {\"layout\":{\"inherit\":true}} -->\n<div class=\"wp-block-group\"><!-- wp:group {\"className\":\"alignwide\"} -->\n<div class=\"wp-block-group alignwide\"><!-- wp:post-title {\"level\":1} /--></div>\n<!-- /wp:group --></div>\n<!-- /wp:group --></div>\n<!-- /wp:group -->\nWarning: Trying to access array offset on value of type int in /Applications/MAMP/htdocs/block-based-themes/pattern.php on line 15\n\n<!-- wp:group {\"tagName\":\"main\"} -->\n<main class=\"wp-block-group\">\n  <!-- wp:group {\"layout\":{\"inherit\":true}} -->\n  <div class=\"wp-block-group\">\n    <!-- wp:columns {\"align\":\"wide\",\"className\":\"wp-block-sidebar-on-left\"} -->\n    <div class=\"wp-block-columns alignwide wp-block-sidebar-on-left\">\n      <!-- wp:column {\"width\":\"25.58%\",\"className\":\"wp-block-column-sidebar\"} -->\n      <div\n        class=\"wp-block-column wp-block-column-sidebar\"\n        style=\"flex-basis: 25.58%\"\n      >\n        <!-- wp:template-part {\"slug\":\"sidebar\",\"tagName\":\"div\"} /-->\n      </div>\n      <!-- /wp:column -->\n\n      <!-- wp:column {\"width\":\"68.9999%\"} -->\n      <div class=\"wp-block-column\" style=\"flex-basis: 68.9999%\">\n        <!-- wp:template-part {\"slug\":\"page-content\",\"tagName\":\"div\"} /-->\n      </div>\n      <!-- /wp:column -->\n    </div>\n    <!-- /wp:columns -->\n  </div>\n  <!-- /wp:group -->\n</main>\n<!-- /wp:group -->\n<!-- wp:template-part {\"slug\":\"footer-with-three-columns\",\"tagName\":\"footer\"} /-->\n"},{"title":"Next Blog","html":"<!-- wp:template-part {\"slug\":\"header\",\"tagName\":\"header\"} /-->\n<!-- wp:group {\"align\":\"full\"} -->\n<div class=\"wp-block-group alignfull\">\n\t<!-- wp:pattern {\"slug\":\"next-blog/cover-with-post-title\"} /-->\n\t<!-- wp:group {\"tagName\":\"main\",\"align\":\"full\",\"style\":{\"spacing\":{\"padding\":{\"top\":\"80px\",\"bottom\":\"80px\",\"left\":\"100px\",\"right\":\"100px\"}}},\"layout\":{\"inherit\":true}} -->\n\t<main\n\t\tclass=\"wp-block-group alignfull\"\n\t\tstyle=\"\n\t\t\tpadding-top: 80px;\n\t\t\tpadding-right: 100px;\n\t\t\tpadding-bottom: 80px;\n\t\t\tpadding-left: 100px;\n\t\t\"\n\t>\n\t\t<!-- wp:columns {\"align\":\"wide\",\"style\":{\"spacing\":{\"padding\":{\"right\":\"0px\",\"left\":\"0px\"}}}} -->\n\t\t<div class=\"wp-block-columns alignwide\" style=\"padding-right: 0px; padding-left: 0px\">\n\t\t\t<!-- wp:column {\"width\":\"25%\"} -->\n\t\t\t\t<div class=\"wp-block-column\" style=\"flex-basis: 25%\">\n\t\t\t\t\t<!-- wp:template-part {\"slug\":\"sidebar\",\"theme\":\"next-blog\",\"tagName\":\"div\"} /-->\n\t\t\t\t</div>\n\t\t\t<!-- /wp:column -->\n\n\t\t\t<!-- wp:column {\"width\":\"75%\",\"style\":{\"spacing\":{\"padding\":{\"top\":\"0px\",\"right\":\"0px\",\"bottom\":\"0px\",\"left\":\"0px\"}}}} -->\n\t\t\t<div class=\"wp-block-column\"\n\t\t\t\tstyle=\"\n\t\t\t\t\tpadding-top: 0px;\n\t\t\t\t\tpadding-right: 0px;\n\t\t\t\t\tpadding-bottom: 0px;\n\t\t\t\t\tpadding-left: 0px;\n\t\t\t\t\tflex-basis: 75%;\n\t\t\t\t\">\n\t\t\t\t<!-- wp:group -->\n\t\t\t\t\t<div class=\"wp-block-group\"><!-- wp:latest-posts {\"className\":\"latest-blog\",\"postsToShow\":18,\"displayPostContent\":true,\"excerptLength\":22,\"displayPostDate\":true,\"postLayout\":\"grid\",\"displayFeaturedImage\":true} /--></div>\n\t\t\t\t<!-- /wp:group -->\n\t\t\t</div>\n\t\t\t<!-- /wp:column -->\n\t\t</div>\n\t\t<!-- /wp:columns -->\n\t</main>\n\t<!-- /wp:group -->\n</div>\n<!-- /wp:group -->\n<!-- wp:template-part {\"slug\":\"footer\",\"tagName\":\"footer\"} /-->\n"},{"title":"Catch FSE","html":"<!-- wp:template-part {\"slug\":\"header-with-buttons\",\"tagName\":\"header\"} /-->\n\n<!-- wp:group {\"tagName\":\"main\"} -->\n<main class=\"wp-block-group\">\n\n<!-- wp:group {\"layout\":{\"inherit\":true}} -->\n<div class=\"wp-block-group\">\n    <!-- wp:columns {\"className\":\"wp-block-sidebar-on-left\",\"align\":\"wide\"} -->\n    <div class=\"wp-block-columns alignwide wp-block-sidebar-on-left\">\n        <!-- wp:column {\"className\":\"wp-block-column-sidebar\",\"width\":\"25%\"} -->\n        <div class=\"wp-block-column wp-block-column-sidebar\" style=\"flex-basis:25%\">\n            <!-- wp:template-part {\"slug\":\"sidebar\",\"tagName\":\"div\"} /-->\n        </div>\n        <!-- /wp:column -->\n        <!-- wp:column {\"width\":\"75%\"} -->\n        <div class=\"wp-block-column\" style=\"flex-basis:75%\">\n            <!-- wp:query {\"query\":{\"perPage\":10,\"pages\":0,\"offset\":0,\"postType\":\"post\",\"categoryIds\":[],\"tagIds\":[],\"order\":\"desc\",\"orderBy\":\"date\",\"author\":\"\",\"search\":\"\",\"exclude\":[],\"sticky\":\"\",\"inherit\":false},\"layout\":{\"inherit\":true},\"tagName\":\"div\"} -->\n            <div class=\"wp-block-query\"><!-- wp:post-template {\"align\":\"full\"} -->\n                <!-- wp:group {\"layout\":{\"inherit\":false}} -->\n                <div class=\"wp-block-group\">\n\n                    <!-- wp:post-featured-image {\"isLink\":true} /-->\n                <!-- wp:group {\"className\":\"alignfull wp-block-post-container\", \"align\":\"full\"} -->\n                <div class=\"wp-block-group wp-block-post-container alignfull\">\n                    <!-- wp:post-title {\"isLink\":true} /-->\n\n                    <!-- wp:group {\"className\":\"wp-block-post-meta\",\"layout\":{\"type\":\"flex\",\"allowOrientation\":false}} -->\n                    <div class=\"wp-block-group wp-block-post-meta\">\n                        <!-- wp:post-terms {\"term\":\"category\"} /-->\n\n                        <!-- wp:post-date {\"isLink\":true} /-->\n\n                        <!-- wp:post-author {\"showAvatar\":false} /-->\n\n                        <!-- wp:post-terms {\"term\":\"post_tag\"} /-->\n                    </div>\n                    <!-- /wp:group -->\n\n                    <!-- wp:post-excerpt {\"moreText\":\"Continue Reading\"} /-->\n                </div>\n                <!-- /wp:group -->\n                </div>\n                <!-- /wp:group -->\n                <!-- /wp:post-template -->\n\n                <!-- wp:query-pagination {\"align\":\"full\",\"layout\":{\"type\":\"flex\",\"justifyContent\":\"space-between\"}} -->\n                <!-- wp:query-pagination-previous {\"fontSize\":\"small\"} /-->\n\n                <!-- wp:query-pagination-numbers /-->\n\n                <!-- wp:query-pagination-next {\"fontSize\":\"small\"} /-->\n                <!-- /wp:query-pagination --></div>\n                <!-- /wp:query -->\n        </div>\n        <!-- /wp:column -->\n    </div>\n    <!-- /wp:columns -->\n</div>\n<!-- /wp:group -->\n\n</main>\n<!-- /wp:group -->\n<!-- wp:template-part {\"slug\":\"footer-with-three-columns\",\"tagName\":\"footer\"} /-->\n"},{"title":"Gutenify Business Dark","html":"<!-- wp:template-part {\"slug\":\"header\",\"tagName\":\"header\"} /-->\n<!-- wp:group {\"align\":\"full\"} -->\n<div class=\"wp-block-group alignfull\">\n\t<!-- wp:cover {\"url\":\"http://raw.githubusercontent.com/ellatrix/block-themes-directory/main/themes/gutenify-business-dark/images/hero-banner.jpg\",\"id\":2543,\"dimRatio\":90,\"focalPoint\":{\"x\":\"0.86\",\"y\":\"0.16\"},\"minHeight\":300,\"customGradient\":\"linear-gradient(90deg,rgb(0,0,0) 30%,rgba(150,149,240,0) 96%)\"} -->\n<div class=\"wp-block-cover\" style=\"min-height:300px\"><span aria-hidden=\"true\" class=\"wp-block-cover__background has-background-dim-90 has-background-dim wp-block-cover__gradient-background has-background-gradient\" style=\"background:linear-gradient(90deg,rgb(0,0,0) 30%,rgba(150,149,240,0) 96%)\"></span><img class=\"wp-block-cover__image-background wp-image-2543\" alt=\"\" src=\"http://raw.githubusercontent.com/ellatrix/block-themes-directory/main/themes/gutenify-business-dark/images/hero-banner.jpg\" style=\"object-position:86% 16%\" data-object-fit=\"cover\" data-object-position=\"86% 16%\"/><div class=\"wp-block-cover__inner-container\"><!-- wp:group {\"align\":\"wide\",\"layout\":{\"inherit\":true}} -->\n<div class=\"wp-block-group alignwide\"><!-- wp:post-title {\"textAlign\":\"center\",\"level\":1,\"align\":\"wide\",\"textColor\":\"foreground\",\"fontSize\":\"medium\"} /--></div>\n<!-- /wp:group --></div></div>\n<!-- /wp:cover -->\n\nWarning: Trying to access array offset on value of type int in /Applications/MAMP/htdocs/block-based-themes/pattern.php on line 15\n\n\t<!-- wp:group {\"tagName\":\"main\",\"align\":\"full\",\"style\":{\"spacing\":{\"padding\":{\"top\":\"80px\",\"bottom\":\"80px\",\"left\":\"20px\",\"right\":\"20px\"}}},\"layout\":{\"inherit\":true}} -->\n\t<main\n\t\tclass=\"wp-block-group alignfull\"\n\t\tstyle=\"\n\t\t\tpadding-top: 80px;\n\t\t\tpadding-right: 20px;\n\t\t\tpadding-bottom: 80px;\n\t\t\tpadding-left: 20px;\n\t\t\"\n\t>\n\t\t<!-- wp:columns {\"align\":\"wide\",\"style\":{\"spacing\":{\"padding\":{\"right\":\"0px\",\"left\":\"0px\"}}}} -->\n\t\t<div\n\t\t\tclass=\"wp-block-columns alignwide\"\n\t\t\tstyle=\"padding-right: 0px; padding-left: 0px\"\n\t\t>\n\t\t\t<!-- wp:column {\"width\":\"25%\"} -->\n\t\t\t<div class=\"wp-block-column\" style=\"flex-basis: 25%\">\n\t\t\t\t<!-- wp:template-part {\"slug\":\"sidebar\",\"theme\":\"gutenify-business-dark\",\"tagName\":\"div\"} /-->\n\t\t\t</div>\n\t\t\t<!-- /wp:column -->\n\n\t\t\t<!-- wp:column -->\n\t\t\t<div class=\"wp-block-column\"></div>\n\t\t\t<!-- /wp:column -->\n\n\t\t\t<!-- wp:column {\"width\":\"75%\",\"style\":{\"spacing\":{\"padding\":{\"top\":\"0px\",\"right\":\"0px\",\"bottom\":\"0px\",\"left\":\"0px\"}}}} -->\n\t\t\t<div\n\t\t\t\tclass=\"wp-block-column\"\n\t\t\t\tstyle=\"\n\t\t\t\t\tpadding-top: 0px;\n\t\t\t\t\tpadding-right: 0px;\n\t\t\t\t\tpadding-bottom: 0px;\n\t\t\t\t\tpadding-left: 0px;\n\t\t\t\t\tflex-basis: 75%;\n\t\t\t\t\"\n\t\t\t>\n\t\t\t\t<!-- wp:query {\"queryId\":1,\"query\":{\"perPage\":\"8\",\"pages\":\"\",\"offset\":\"\",\"postType\":\"post\",\"order\":\"desc\",\"orderBy\":\"date\",\"author\":\"\",\"search\":\"\",\"exclude\":[],\"sticky\":\"\",\"inherit\":true},\"tagName\":\"main\",\"displayLayout\":{\"type\":\"flex\",\"columns\":2},\"align\":\"wide\",\"layout\":{\"inherit\":true}} -->\n\t\t\t\t<main class=\"wp-block-query alignwide\">\n\t\t\t\t\t<!-- wp:post-template {\"align\":\"wide\"} -->\n\t\t\t\t\t<!-- wp:group {\"style\":{\"spacing\":{\"padding\":{\"top\":\"0px\",\"right\":\"0px\",\"bottom\":\"0px\",\"left\":\"0px\"}}},\"className\":\"has-shadow-dark animated animated-fadeInUp\",\"layout\":{\"inherit\":true}} -->\n\t\t\t\t\t<div\n\t\t\t\t\t\tclass=\"wp-block-group has-shadow-dark animated animated-fadeInUp\"\n\t\t\t\t\t\tstyle=\"\n\t\t\t\t\t\t\tpadding-top: 0px;\n\t\t\t\t\t\t\tpadding-right: 0px;\n\t\t\t\t\t\t\tpadding-bottom: 0px;\n\t\t\t\t\t\t\tpadding-left: 0px;\n\t\t\t\t\t\t\"\n\t\t\t\t\t>\n\t\t\t\t\t\t<!-- wp:post-featured-image {\"isLink\":true,\"align\":\"wide\",\"className\":\"no-padding\"} /-->\n\n\t\t\t\t\t\t<!-- wp:group {\"align\":\"wide\",\"style\":{\"spacing\":{\"padding\":{\"top\":\"40px\",\"right\":\"40px\",\"bottom\":\"40px\",\"left\":\"40px\"},\"margin\":{\"top\":\"0px\"}}},\"backgroundColor\":\"dark-gray\"} -->\n\t\t\t\t\t\t<div\n\t\t\t\t\t\t\tclass=\"wp-block-group alignwide has-dark-gray-background-color has-background\"\n\t\t\t\t\t\t\tstyle=\"\n\t\t\t\t\t\t\t\tmargin-top: 0px;\n\t\t\t\t\t\t\t\tpadding-top: 40px;\n\t\t\t\t\t\t\t\tpadding-right: 40px;\n\t\t\t\t\t\t\t\tpadding-bottom: 40px;\n\t\t\t\t\t\t\t\tpadding-left: 40px;\n\t\t\t\t\t\t\t\"\n\t\t\t\t\t\t>\n\t\t\t\t\t\t\t<!-- wp:post-title {\"level\":3,\"isLink\":true,\"align\":\"wide\",\"style\":{\"typography\":{\"fontStyle\":\"normal\",\"fontWeight\":\"600\",\"lineHeight\":\"1.4\",\"fontSize\":\"1.3rem\"}}} /-->\n\n\t\t\t\t\t\t\t<!-- wp:group {\"layout\":{\"type\":\"flex\",\"flexWrap\":\"nowrap\"}} -->\n\t\t\t\t\t\t\t<div class=\"wp-block-group\">\n\t\t\t\t\t\t\t\t<!-- wp:post-author {\"avatarSize\":24,\"showBio\":false,\"fontSize\":\"small\"} /-->\n\n\t\t\t\t\t\t\t\t<!-- wp:post-date {\"format\":\"M j, Y\",\"isLink\":true,\"fontSize\":\"small\"} /-->\n\t\t\t\t\t\t\t</div>\n\t\t\t\t\t\t\t<!-- /wp:group -->\n\n\t\t\t\t\t\t\t<!-- wp:post-excerpt {\"moreText\":\"Know More\",\"style\":{\"elements\":{\"link\":{\"color\":{\"text\":\"var:preset|color|primary\"}}}}} /-->\n\t\t\t\t\t\t</div>\n\t\t\t\t\t\t<!-- /wp:group -->\n\t\t\t\t\t</div>\n\t\t\t\t\t<!-- /wp:group -->\n\n\t\t\t\t\t<!-- wp:spacer {\"height\":\"20px\"} -->\n\t\t\t\t\t<div\n\t\t\t\t\t\tstyle=\"height: 20px\"\n\t\t\t\t\t\taria-hidden=\"true\"\n\t\t\t\t\t\tclass=\"wp-block-spacer\"\n\t\t\t\t\t></div>\n\t\t\t\t\t<!-- /wp:spacer -->\n\t\t\t\t\t<!-- /wp:post-template -->\n\n\t\t\t\t\t<!-- wp:query-pagination {\"paginationArrow\":\"arrow\",\"align\":\"center\",\"layout\":{\"type\":\"flex\",\"justifyContent\":\"space-between\"}} -->\n\t\t\t\t\t<!-- wp:query-pagination-previous {\"fontSize\":\"small\"} /-->\n\n\t\t\t\t\t<!-- wp:query-pagination-numbers /-->\n\n\t\t\t\t\t<!-- wp:query-pagination-next {\"fontSize\":\"small\"} /-->\n\t\t\t\t\t<!-- /wp:query-pagination -->\n\t\t\t\t</main>\n\t\t\t\t<!-- /wp:query -->\n\t\t\t</div>\n\t\t\t<!-- /wp:column -->\n\t\t</div>\n\t\t<!-- /wp:columns -->\n\t</main>\n\t<!-- /wp:group -->\n</div>\n<!-- /wp:group -->\n<!-- wp:template-part {\"slug\":\"footer\",\"tagName\":\"footer\"} /-->\n"},{"title":"Rhythmic","html":"<!-- wp:template-part {\"slug\":\"header\",\"tagName\":\"header\"} /-->\n<!-- wp:group {\"align\":\"full\",\"className\":\"no-margin-top banner\",\"style\":{\"spacing\":{\"padding\":{\"top\":\"0px\",\"right\":\"0px\",\"bottom\":\"0px\",\"left\":\"0px\"}}},\"layout\":{\"inherit\":false}} -->\n<div class=\"wp-block-group alignfull banner\" style=\"padding-top:0px;padding-right:0px;padding-bottom:0px;padding-left:0px\">\n\t<!-- wp:cover {\"url\":\"http://raw.githubusercontent.com/ellatrix/block-themes-directory/main/themes/rhythmic/assets/images/banner.jpg\",\"dimRatio\":0,\"overlayColor\":\"body-text\"} -->\n\t<div class=\"wp-block-cover\">\n\t\t<span aria-hidden=\"true\" class=\"wp-block-cover__background has-body-text-background-color has-background-dim-0 has-background-dim\"></span>\n\t\t<img class=\"wp-block-cover__image-background\" alt=\"\" src=\"http://raw.githubusercontent.com/ellatrix/block-themes-directory/main/themes/rhythmic/assets/images/banner.jpg\" data-object-fit=\"cover\"/>\n\t\t<div class=\"wp-block-cover__inner-container\">\n\t\t\t<!-- wp:group {\"layout\":{\"inherit\":true}} -->\n\t\t\t<div class=\"wp-block-group\">\n\t\t\t\t<!-- wp:group {\"className\":\"alignwide\"} -->\n\t\t\t\t<div class=\"wp-block-group alignwide\">\n\t\t\t\t\t<!-- wp:post-title {\"level\":1,\"textColor\":\"foreground\",\"textAlign\":\"center\"} /-->\n\t\t\t\t</div>\n\t\t\t\t<!-- /wp:group -->\n\t\t\t</div>\n\t\t\t<!-- /wp:group -->\n\t\t</div>\n\t</div>\n\t<!-- /wp:cover -->\n</div>\n<!-- /wp:group -->\nWarning: Trying to access array offset on value of type int in /Applications/MAMP/htdocs/block-based-themes/pattern.php on line 15\n\n<!-- wp:group {\"tagName\":\"main\"} -->\n<main class=\"wp-block-group\">\n  <!-- wp:group {\"layout\":{\"inherit\":true}} -->\n  <div class=\"wp-block-group\">\n    <!-- wp:columns {\"align\":\"wide\",\"className\":\"wp-block-sidebar-on-left\"} -->\n    <div class=\"wp-block-columns alignwide wp-block-sidebar-on-left\">\n      <!-- wp:column {\"width\":\"22.9%\",\"className\":\"wp-block-column-sidebar\"} -->\n      <div\n        class=\"wp-block-column wp-block-column-sidebar\"\n        style=\"flex-basis: 22.9%\"\n      >\n        <!-- wp:template-part {\"slug\":\"sidebar\",\"tagName\":\"div\"} /-->\n      </div>\n      <!-- /wp:column -->\n\n      <!-- wp:column {\"width\":\"68.6%\"} -->\n      <div class=\"wp-block-column\" style=\"flex-basis: 68.6%\">\n        <!-- wp:template-part {\"slug\":\"page-content\",\"tagName\":\"div\"} /-->\n      </div>\n      <!-- /wp:column -->\n    </div>\n    <!-- /wp:columns -->\n  </div>\n  <!-- /wp:group -->\n</main>\n<!-- /wp:group -->\n<!-- wp:template-part {\"slug\":\"footer-with-four-columns\",\"tagName\":\"footer\"} /-->\n"},{"title":"VW Bakery Blocks","html":"<!-- wp:template-part {\"slug\":\"header\",\"tagName\":\"header\"} /-->\n<!-- wp:group {\"align\":\"full\"} -->\n<div class=\"wp-block-group alignfull\">\n\t<!-- wp:cover {\"url\":\"http://raw.githubusercontent.com/ellatrix/block-themes-directory/main/themes/vw-bakery-blocks/images/hero-banner.png\",\"id\":123,\"dimRatio\":70,\"overlayColor\":\"black\",\"focalPoint\":{\"x\":\"0.00\",\"y\":\"0.00\"},\"minHeight\":300,\"className\":\"innerpage-banner\"} -->\n<div class=\"wp-block-cover innerpage-banner\" style=\"min-height:300px\"><span aria-hidden=\"true\" class=\"wp-block-cover__background has-black-background-color has-background-dim-70 has-background-dim\"></span><img class=\"wp-block-cover__image-background wp-image-123\" alt=\"\" src=\"http://raw.githubusercontent.com/ellatrix/block-themes-directory/main/themes/vw-bakery-blocks/images/hero-banner.png\" style=\"object-position:0% 0%\" data-object-fit=\"cover\" data-object-position=\"0% 0%\"/><div class=\"wp-block-cover__inner-container\"><!-- wp:group {\"align\":\"wide\",\"layout\":{\"inherit\":true}} -->\n<div class=\"wp-block-group alignwide\"><!-- wp:post-title {\"textAlign\":\"center\",\"level\":1,\"align\":\"wide\",\"style\":{\"typography\":{\"fontSize\":\"35px\",\"fontStyle\":\"normal\",\"fontWeight\":\"700\"}},\"textColor\":\"white\"} /--></div>\n<!-- /wp:group -->\n\n<!-- wp:image {\"id\":94,\"sizeSlug\":\"full\",\"linkDestination\":\"none\",\"className\":\"title-img\"} -->\n<figure class=\"wp-block-image size-full title-img\"><img src=\"http://raw.githubusercontent.com/ellatrix/block-themes-directory/main/themes/vw-bakery-blocks/images/title-image1.png\" alt=\"\" class=\"wp-image-94\"/></figure>\n<!-- /wp:image --></div></div>\n<!-- /wp:cover -->\nWarning: Trying to access array offset on value of type int in /Applications/MAMP/htdocs/block-based-themes/pattern.php on line 15\n\n\t<!-- wp:group {\"tagName\":\"main\",\"align\":\"full\",\"style\":{\"spacing\":{\"padding\":{\"top\":\"80px\",\"bottom\":\"80px\",\"left\":\"100px\",\"right\":\"100px\"}}},\"layout\":{\"inherit\":true}} -->\n\t<main\n\t\tclass=\"wp-block-group alignfull\"\n\t\tstyle=\"\n\t\t\tpadding-top: 80px;\n\t\t\tpadding-right: 100px;\n\t\t\tpadding-bottom: 80px;\n\t\t\tpadding-left: 100px;\n\t\t\"\n\t>\n\t\t<!-- wp:columns {\"align\":\"wide\",\"style\":{\"spacing\":{\"padding\":{\"right\":\"0px\",\"left\":\"0px\"}}}} -->\n\t\t<div class=\"wp-block-columns alignwide\" style=\"padding-right: 0px; padding-left: 0px\">\n\t\t\t<!-- wp:column {\"width\":\"25%\"} -->\n\t\t\t\t<div class=\"wp-block-column\" style=\"flex-basis: 25%\">\n\t\t\t\t\t<!-- wp:template-part {\"slug\":\"sidebar\",\"theme\":\"vw-bakery-blocks\",\"tagName\":\"div\"} /-->\n\t\t\t\t</div>\n\t\t\t<!-- /wp:column -->\n\n\t\t\t<!-- wp:column {\"width\":\"75%\",\"style\":{\"spacing\":{\"padding\":{\"top\":\"0px\",\"right\":\"0px\",\"bottom\":\"0px\",\"left\":\"0px\"}}}} -->\n\t\t\t<div class=\"wp-block-column\"\n\t\t\t\tstyle=\"\n\t\t\t\t\tpadding-top: 0px;\n\t\t\t\t\tpadding-right: 0px;\n\t\t\t\t\tpadding-bottom: 0px;\n\t\t\t\t\tpadding-left: 0px;\n\t\t\t\t\tflex-basis: 75%;\n\t\t\t\t\">\n\t\t\t\t<!-- wp:group -->\n\t\t\t\t\t<div class=\"wp-block-group\"><!-- wp:latest-posts {\"postsToShow\":18,\"displayPostContent\":true,\"excerptLength\":22,\"displayPostDate\":true,\"postLayout\":\"grid\",\"displayFeaturedImage\":true} /--></div>\n\t\t\t\t<!-- /wp:group -->\n\t\t\t</div>\n\t\t\t<!-- /wp:column -->\n\t\t</div>\n\t\t<!-- /wp:columns -->\n\t</main>\n\t<!-- /wp:group -->\n</div>\n<!-- /wp:group -->\n<!-- wp:template-part {\"slug\":\"footer\",\"tagName\":\"footer\"} /-->\n"},{"title":"Gutenify Magazine","html":"<!-- wp:template-part {\"slug\":\"header\",\"tagName\":\"header\"} /-->\n<!-- wp:group {\"tagName\":\"main\",\"align\":\"full\",\"style\":{\"spacing\":{\"padding\":{\"top\":\"80px\",\"bottom\":\"80px\",\"left\":\"20px\",\"right\":\"20px\"}}},\"layout\":{\"inherit\":true}} -->\n<main\n  class=\"wp-block-group alignfull\"\n  style=\"\n    padding-top: 80px;\n    padding-right: 20px;\n    padding-bottom: 80px;\n    padding-left: 20px;\n  \"\n>\n  <!-- wp:columns {\"align\":\"wide\",\"style\":{\"spacing\":{\"padding\":{\"right\":\"0px\",\"left\":\"0px\"}}}} -->\n  <div\n    class=\"wp-block-columns alignwide\"\n    style=\"padding-right: 0px; padding-left: 0px\"\n  >\n    <!-- wp:column {\"width\":\"25%\"} -->\n    <div class=\"wp-block-column\" style=\"flex-basis: 25%\">\n      <!-- wp:template-part {\"slug\":\"sidebar\",\"theme\":\"gutenify-magazine\",\"tagName\":\"div\"} /-->\n    </div>\n    <!-- /wp:column -->\n\n    <!-- wp:column -->\n    <div class=\"wp-block-column\"></div>\n    <!-- /wp:column -->\n\n    <!-- wp:column {\"width\":\"75%\",\"style\":{\"spacing\":{\"padding\":{\"top\":\"0px\",\"right\":\"0px\",\"bottom\":\"0px\",\"left\":\"0px\"}}}} -->\n    <div\n      class=\"wp-block-column\"\n      style=\"\n        padding-top: 0px;\n        padding-right: 0px;\n        padding-bottom: 0px;\n        padding-left: 0px;\n        flex-basis: 75%;\n      \"\n    >\n      <!-- wp:group {\"style\":{\"color\":{\"background\":\"#f1f1f1\"},\"spacing\":{\"padding\":{\"top\":\"10px\",\"right\":\"20px\",\"bottom\":\"10px\",\"left\":\"20px\"}}},\"className\":\"animated animated-fadeInUp\",\"fontSize\":\"small\"} -->\n      <div\n        class=\"wp-block-group animated animated-fadeInUp has-background has-small-font-size\"\n        style=\"\n          background-color: #f1f1f1;\n          padding-top: 10px;\n          padding-right: 20px;\n          padding-bottom: 10px;\n          padding-left: 20px;\n        \"\n      >\n        <!-- wp:post-title /-->\n      </div>\n      <!-- /wp:group -->\n\n     <!-- wp:query {\"queryId\":1,\"query\":{\"perPage\":\"8\",\"pages\":\"\",\"offset\":\"\",\"postType\":\"post\",\"order\":\"desc\",\"orderBy\":\"date\",\"author\":\"\",\"search\":\"\",\"exclude\":[],\"sticky\":\"\",\"inherit\":true},\"tagName\":\"main\",\"displayLayout\":{\"type\":\"flex\",\"columns\":2},\"align\":\"wide\",\"layout\":{\"inherit\":true}} -->\n<main class=\"wp-block-query alignwide\">\n\t<!-- wp:post-template {\"align\":\"wide\"} -->\n\t<!-- wp:group {\"style\":{\"spacing\":{\"padding\":{\"top\":\"0px\",\"right\":\"0px\",\"bottom\":\"0px\",\"left\":\"0px\"}}},\"className\":\"has-shadow-dark animated animated-fadeInUp\",\"layout\":{\"inherit\":true}} -->\n\t<div\n\t\tclass=\"wp-block-group has-shadow-dark animated animated-fadeInUp\"\n\t\tstyle=\"\n\t\t\tpadding-top: 0px;\n\t\t\tpadding-right: 0px;\n\t\t\tpadding-bottom: 0px;\n\t\t\tpadding-left: 0px;\n\t\t\"\n\t>\n\t\t<!-- wp:post-featured-image {\"isLink\":true,\"align\":\"wide\",\"className\":\"no-padding\"} /-->\n\n\t\t<!-- wp:group {\"align\":\"wide\",\"style\":{\"spacing\":{\"padding\":{\"top\":\"40px\",\"right\":\"40px\",\"bottom\":\"40px\",\"left\":\"40px\"},\"margin\":{\"top\":\"0px\"}}}} -->\n\t\t<div\n\t\t\tclass=\"wp-block-group alignwide\"\n\t\t\tstyle=\"\n\t\t\t\tmargin-top: 0px;\n\t\t\t\tpadding-top: 40px;\n\t\t\t\tpadding-right: 40px;\n\t\t\t\tpadding-bottom: 40px;\n\t\t\t\tpadding-left: 40px;\n\t\t\t\"\n\t\t>\n\t\t\t<!-- wp:post-title {\"level\":3,\"isLink\":true,\"align\":\"wide\",\"style\":{\"typography\":{\"fontStyle\":\"normal\",\"fontWeight\":\"600\",\"lineHeight\":\"1.4\",\"fontSize\":\"1.3rem\"}}} /-->\n\n\t\t\t<!-- wp:group {\"layout\":{\"type\":\"flex\",\"flexWrap\":\"nowrap\"}} -->\n\t\t\t<div class=\"wp-block-group\">\n\t\t\t\t<!-- wp:post-author {\"avatarSize\":24,\"showBio\":false,\"fontSize\":\"small\"} /-->\n\n\t\t\t\t<!-- wp:post-date {\"format\":\"M j, Y\",\"isLink\":true,\"fontSize\":\"small\"} /-->\n\t\t\t</div>\n\t\t\t<!-- /wp:group -->\n\n\t\t\t<!-- wp:post-excerpt {\"moreText\":\"Know More\",\"style\":{\"elements\":{\"link\":{\"color\":{\"text\":\"var:preset|color|primary\"}}}}} /-->\n\t\t</div>\n\t\t<!-- /wp:group -->\n\t</div>\n\t<!-- /wp:group -->\n\n\t<!-- wp:spacer {\"height\":\"20px\"} -->\n\t<div style=\"height: 20px\" aria-hidden=\"true\" class=\"wp-block-spacer\"></div>\n\t<!-- /wp:spacer -->\n\t<!-- /wp:post-template -->\n\n\t<!-- wp:query-pagination {\"paginationArrow\":\"arrow\",\"align\":\"center\",\"layout\":{\"type\":\"flex\",\"justifyContent\":\"space-between\"}} -->\n\t<!-- wp:query-pagination-previous {\"fontSize\":\"small\"} /-->\n\n\t<!-- wp:query-pagination-numbers /-->\n\n\t<!-- wp:query-pagination-next {\"fontSize\":\"small\"} /-->\n\t<!-- /wp:query-pagination -->\n</main>\n<!-- /wp:query -->\n\nWarning: Trying to access array offset on value of type int in /Applications/MAMP/htdocs/block-based-themes/pattern.php on line 15\n\n    </div>\n    <!-- /wp:column -->\n  </div>\n  <!-- /wp:columns -->\n</main>\n<!-- /wp:group -->\n<!-- wp:template-part {\"slug\":\"footer\",\"tagName\":\"footer\"} /-->\n"},{"title":"Gutenify Template Kit","html":"<!-- wp:template-part {\"slug\":\"header\",\"tagName\":\"header\"} /-->\n<!-- wp:group {\"tagName\":\"main\",\"className\":\"no-margin no-padding\"} -->\n<main class=\"wp-block-group no-margin no-padding\">\n    <!-- wp:group {\"layout\":{\"inherit\":true}} -->\n    <div class=\"wp-block-group\">\n        <!-- wp:cover {\"url\":\"http://raw.githubusercontent.com/ellatrix/block-themes-directory/main/themes/gutenify-template-kit/images/single-header.png\",\"id\":172,\"dimRatio\":90,\"focalPoint\":{\"x\":\"0.58\",\"y\":\"0.18\"},\"minHeight\":400,\"minHeightUnit\":\"px\",\"customGradient\":\"linear-gradient(135deg,rgb(76,15,242) 0%,rgb(155,81,224) 100%)\",\"contentPosition\":\"center center\",\"align\":\"full\"} -->\n        <div class=\"wp-block-cover alignfull\" style=\"min-height:400px\"><span aria-hidden=\"true\"\n                class=\"wp-block-cover__background has-background-dim-90 has-background-dim wp-block-cover__gradient-background has-background-gradient\"\n                style=\"background:linear-gradient(135deg,rgb(76,15,242) 0%,rgb(155,81,224) 100%)\"></span><img\n                class=\"wp-block-cover__image-background wp-image-172\" alt=\"\"\n                src=\"http://raw.githubusercontent.com/ellatrix/block-themes-directory/main/themes/gutenify-template-kit/images/single-header.png\"\n                style=\"object-position:58% 18%\" data-object-fit=\"cover\" data-object-position=\"58% 18%\" />\n            <div class=\"wp-block-cover__inner-container\">\n               <!-- wp:post-title {\"textAlign\":\"center\",\"level\":1,\"align\":\"wide\",\"style\":{\"spacing\":{\"margin\":{\"bottom\":\"0px\",\"top\":\"0px\"}}},\"textColor\":\"background\",\"fontSize\":\"large\"} /-->\n            </div>\n        </div>\n        <!-- /wp:cover -->\n    </div>\n    <!-- /wp:group -->\n</main>\n<!-- /wp:group -->\n\nWarning: Trying to access array offset on value of type int in /Applications/MAMP/htdocs/block-based-themes/pattern.php on line 15\n\n\n<!-- wp:group {\"tagName\":\"main\",\"align\":\"full\",\"style\":{\"spacing\":{\"padding\":{\"top\":\"80px\",\"bottom\":\"80px\",\"left\":\"30px\",\"right\":\"30px\"}}},\"className\":\"no-margin no-padding\",\"layout\":{\"inherit\":true}} -->\n<main class=\"wp-block-group alignfull no-margin no-padding\"\n\tstyle=\"padding-top:80px;padding-right:30px;padding-bottom:80px;padding-left:30px\">\n\t<!-- wp:columns {\"align\":\"wide\"} -->\n\t<div class=\"wp-block-columns alignwide\">\n\t\t<!-- wp:column {\"width\":\"33.33%\"} -->\n\t\t<div class=\"wp-block-column\" style=\"flex-basis:33.33%\">\n\t\t\t<!-- wp:template-part {\"slug\":\"sidebar\",\"tagName\":\"div\"} /-->\n\t\t</div>\n\t\t<!-- /wp:column -->\n\n\t\t<!-- wp:column -->\n\t\t<div class=\"wp-block-column\">\n\t\t</div>\n\t\t<!-- /wp:column -->\n\n\t\t<!-- wp:column {\"width\":\"66.66%\",\"style\":{\"spacing\":{\"padding\":{\"top\":\"0px\",\"right\":\"0px\",\"bottom\":\"0px\",\"left\":\"0px\"}}}} -->\n\t\t<div class=\"wp-block-column\"\n\t\t\tstyle=\"padding-top:0px;padding-right:0px;padding-bottom:0px;padding-left:0px;flex-basis:66.66%\">\n\t\t\t<!-- wp:query {\"queryId\":1,\"query\":{\"perPage\":\"3\",\"pages\":\"\",\"offset\":\"\",\"postType\":\"post\",\"order\":\"desc\",\"orderBy\":\"date\",\"author\":\"\",\"search\":\"\",\"exclude\":[],\"sticky\":\"\",\"inherit\":true},\"tagName\":\"main\",\"displayLayout\":{\"type\":\"flex\",\"columns\":2},\"align\":\"wide\",\"layout\":{\"inherit\":true}} -->\n<main class=\"wp-block-query alignwide\">\n        <!-- wp:post-template {\"align\":\"wide\"} -->\n        <!-- wp:group {\"style\":{\"spacing\":{\"padding\":{\"top\":\"0px\",\"right\":\"0px\",\"bottom\":\"0px\",\"left\":\"0px\"}}},\"className\":\"has-shadow-dark\",\"layout\":{\"inherit\":true}} -->\n        <div class=\"wp-block-group has-shadow-dark\"\n                style=\"padding-top:0px;padding-right:0px;padding-bottom:0px;padding-left:0px\">\n                <!-- wp:post-featured-image {\"isLink\":true,\"align\":\"wide\",\"className\":\"no-padding\"} /-->\n\n                <!-- wp:group {\"align\":\"wide\",\"style\":{\"spacing\":{\"padding\":{\"top\":\"40px\",\"right\":\"40px\",\"bottom\":\"40px\",\"left\":\"40px\"},\"margin\":{\"top\":\"0px\"}}}} -->\n                <div class=\"wp-block-group alignwide\"\n                        style=\"margin-top:0px;padding-top:40px;padding-right:40px;padding-bottom:40px;padding-left:40px\">\n                        <!-- wp:post-title {\"isLink\":true,\"align\":\"wide\",\"style\":{\"typography\":{\"fontStyle\":\"normal\",\"fontWeight\":\"400\"}},\"fontSize\":\"medium\"} /-->\n\n                        <!-- wp:post-date {\"format\":\"F j, Y\",\"isLink\":true,\"style\":{\"typography\":{\"fontStyle\":\"italic\",\"fontWeight\":\"400\"}},\"fontSize\":\"small\"} /-->\n\n                        <!-- wp:post-excerpt /-->\n                </div>\n                <!-- /wp:group -->\n        </div>\n        <!-- /wp:group -->\n\n        <!-- wp:spacer {\"height\":\"20px\"} -->\n        <div style=\"height:20px\" aria-hidden=\"true\" class=\"wp-block-spacer\"></div>\n        <!-- /wp:spacer -->\n        <!-- /wp:post-template -->\n\n        <!-- wp:query-pagination {\"paginationArrow\":\"arrow\",\"align\":\"center\",\"layout\":{\"type\":\"flex\",\"justifyContent\":\"space-between\"}} -->\n        <!-- wp:query-pagination-previous {\"fontSize\":\"small\"} /-->\n\n        <!-- wp:query-pagination-numbers /-->\n\n        <!-- wp:query-pagination-next {\"fontSize\":\"small\"} /-->\n        <!-- /wp:query-pagination -->\n</main>\n<!-- /wp:query -->\n\nWarning: Trying to access array offset on value of type int in /Applications/MAMP/htdocs/block-based-themes/pattern.php on line 15\n\n\t\t</div>\n\t\t<!-- /wp:column -->\n\t</div>\n\t<!-- /wp:columns -->\n</main>\n<!-- /wp:group -->\n\n<!-- wp:template-part {\"slug\":\"footer\",\"tagName\":\"footer\"} /-->\n"},{"title":"Axton","html":"<!-- wp:template-part {\"slug\":\"header-with-search-bar\",\"tagName\":\"header\"} /-->\n\n\n<!-- wp:group {\"tagName\":\"main\"} -->\n<main class=\"wp-block-group\"><!-- wp:group {\"layout\":{\"inherit\":true}} -->\n    <div class=\"wp-block-group\"><!-- wp:columns {\"align\":\"wide\",\"className\":\"wp-block-sidebar-on-left\"} -->\n    <div class=\"wp-block-columns alignwide wp-block-sidebar-on-left\"><!-- wp:column {\"width\":\"25%\",\"className\":\"wp-block-column-sidebar\"} -->\n    <div class=\"wp-block-column wp-block-column-sidebar\" style=\"flex-basis:25%\"><!-- wp:template-part {\"slug\":\"sidebar\",\"theme\":\"axton\",\"tagName\":\"div\"} /--></div>\n    <!-- /wp:column -->\n    \n    <!-- wp:column {\"width\":\"75%\"} -->\n    <div class=\"wp-block-column\" style=\"flex-basis:75%\"><!-- wp:query {\"queryId\":0,\"query\":{\"perPage\":10,\"pages\":0,\"offset\":0,\"postType\":\"post\",\"order\":\"desc\",\"orderBy\":\"date\",\"author\":\"\",\"search\":\"\",\"exclude\":[],\"sticky\":\"\",\"inherit\":false},\"displayLayout\":{\"type\":\"list\"},\"layout\":{\"inherit\":true}} -->\n    <div class=\"wp-block-query\"><!-- wp:post-template {\"align\":\"full\"} -->\n    <!-- wp:group {\"layout\":{\"inherit\":false}} -->\n    <div class=\"wp-block-group\"><!-- wp:columns -->\n    <div class=\"wp-block-columns\"><!-- wp:column -->\n    <div class=\"wp-block-column\"><!-- wp:post-featured-image {\"isLink\":true} /--></div>\n    <!-- /wp:column -->\n    \n    <!-- wp:column -->\n    <div class=\"wp-block-column\"><!-- wp:group {\"align\":\"full\",\"className\":\"alignfull wp-block-post-container\"} -->\n    <div class=\"wp-block-group alignfull wp-block-post-container\"><!-- wp:group {\"className\":\"wp-block-post-meta\",\"layout\":{\"type\":\"flex\",\"allowOrientation\":false}} -->\n    <div class=\"wp-block-group wp-block-post-meta\"><!-- wp:post-terms {\"term\":\"category\"} /--></div>\n    <!-- /wp:group -->\n    \n    <!-- wp:post-title {\"isLink\":true} /-->\n    \n    <!-- wp:post-excerpt {\"moreText\":\"Continue Reading\"} /--></div>\n    <!-- /wp:group --></div>\n    <!-- /wp:column --></div>\n    <!-- /wp:columns --></div>\n    <!-- /wp:group -->\n    <!-- /wp:post-template -->\n    \n    <!-- wp:query-pagination {\"align\":\"wide\",\"layout\":{\"type\":\"flex\",\"justifyContent\":\"space-between\"}} -->\n    <!-- wp:query-pagination-previous {\"fontSize\":\"small\"} /-->\n    \n    <!-- wp:query-pagination-numbers /-->\n    \n    <!-- wp:query-pagination-next {\"fontSize\":\"small\"} /-->\n    <!-- /wp:query-pagination --></div>\n    <!-- /wp:query --></div>\n    <!-- /wp:column --></div>\n    <!-- /wp:columns --></div>\n    <!-- /wp:group --></main>\n    <!-- /wp:group -->\n<!-- wp:template-part {\"slug\":\"footer-with-three-columns\",\"tagName\":\"footer\"} /-->\n\n\n\n"},{"title":"Hello Gutenify","html":"<!-- wp:template-part {\"slug\":\"header\",\"tagName\":\"header\"} /-->\n\n<!-- wp:group {\"tagName\":\"main\",\"align\":\"full\",\"style\":{\"spacing\":{\"padding\":{\"top\":\"80px\",\"bottom\":\"80px\",\"left\":\"30px\",\"right\":\"30px\"}}},\"className\":\"no-margin no-padding\",\"layout\":{\"inherit\":true}} -->\n<main class=\"wp-block-group alignfull no-margin no-padding\"\n\tstyle=\"padding-top:80px;padding-right:30px;padding-bottom:80px;padding-left:30px\">\n\t<!-- wp:columns {\"align\":\"wide\"} -->\n\t<div class=\"wp-block-columns alignwide\">\n\t\t<!-- wp:column {\"width\":\"33.33%\"} -->\n\t\t<div class=\"wp-block-column\" style=\"flex-basis:33.33%\">\n\t\t\t<!-- wp:template-part {\"slug\":\"sidebar\",\"tagName\":\"div\"} /-->\n\t\t</div>\n\t\t<!-- /wp:column -->\n\n\t\t<!-- wp:column -->\n\t\t<div class=\"wp-block-column\">\n\t\t</div>\n\t\t<!-- /wp:column -->\n\n\t\t<!-- wp:column {\"width\":\"66.66%\",\"style\":{\"spacing\":{\"padding\":{\"top\":\"0px\",\"right\":\"0px\",\"bottom\":\"0px\",\"left\":\"0px\"}}}} -->\n\t\t<div class=\"wp-block-column\"\n\t\t\tstyle=\"padding-top:0px;padding-right:0px;padding-bottom:0px;padding-left:0px;flex-basis:66.66%\">\n\t\t\t<!-- wp:post-title {\"level\":1,\"align\":\"wide\",\"style\":{\"typography\":{\"fontSize\":\"clamp(2.75rem, 6vw, 3.25rem)\"},\"spacing\":{\"margin\":{\"bottom\":\"1rem\"}}}} /-->\n\t\t\t<!-- wp:query {\"queryId\":1,\"query\":{\"perPage\":\"3\",\"pages\":\"\",\"offset\":\"\",\"postType\":\"post\",\"order\":\"desc\",\"orderBy\":\"date\",\"author\":\"\",\"search\":\"\",\"exclude\":[],\"sticky\":\"\",\"inherit\":false},\"tagName\":\"main\",\"displayLayout\":{\"type\":\"flex\",\"columns\":2},\"align\":\"wide\",\"layout\":{\"inherit\":true}} -->\n<main class=\"wp-block-query alignwide\">\n        <!-- wp:post-template {\"align\":\"wide\"} -->\n        <!-- wp:group {\"layout\":{\"inherit\":true}} -->\n        <div class=\"wp-block-group\">\n\n                <!-- wp:post-featured-image {\"isLink\":true,\"align\":\"wide\"} /-->\n                <!-- wp:columns {\"align\":\"wide\"} -->\n                <div class=\"wp-block-columns alignwide hello-gutenify-post-content\">\n                        <!-- wp:column {\"width\":\"\"} -->\n                        <div class=\"wp-block-column\">\n                                <!-- wp:post-title {\"isLink\":true,\"align\":\"wide\",\"fontSize\":\"var(--wp--custom--typography--font-size--huge, clamp(2.25rem, 4vw, 2.75rem))\"} /-->\n                                <!-- wp:post-excerpt /-->\n\n                                <!-- wp:post-date {\"format\":\"F j, Y\",\"isLink\":true,\"style\":{\"typography\":{\"fontStyle\":\"italic\",\"fontWeight\":\"400\"}},\"fontSize\":\"small\"} /-->\n                        </div>\n                        <!-- /wp:column -->\n                </div>\n                <!-- /wp:columns -->\n\n        </div>\n        <!-- /wp:group -->\n        <!-- wp:spacer {\"height\":20} -->\n        <div style=\"height:20px\" aria-hidden=\"true\" class=\"wp-block-spacer\"></div>\n        <!-- /wp:spacer -->\n        <!-- /wp:post-template -->\n\n        <!-- wp:query-pagination {\"paginationArrow\":\"arrow\",\"align\":\"center\",\"layout\":{\"type\":\"flex\",\"justifyContent\":\"space-between\"}} -->\n        <!-- wp:query-pagination-previous {\"fontSize\":\"small\"} /-->\n\n        <!-- wp:query-pagination-numbers /-->\n\n        <!-- wp:query-pagination-next {\"fontSize\":\"small\"} /-->\n        <!-- /wp:query-pagination -->\n</main>\n<!-- /wp:query -->\n\nWarning: Trying to access array offset on value of type int in /Applications/MAMP/htdocs/block-based-themes/pattern.php on line 15\n\n\t\t</div>\n\t\t<!-- /wp:column -->\n\t</div>\n\t<!-- /wp:columns -->\n</main>\n<!-- /wp:group -->\n\n<!-- wp:template-part {\"slug\":\"footer\",\"tagName\":\"footer\"} /-->\n"},{"title":"Edunation","html":"<!-- wp:template-part {\"slug\":\"header\",\"tagName\":\"header\"} /-->\r\n\r\n\n<!-- wp:group {\"align\":\"full\"} -->\n<div class=\"wp-block-group alignfull\"><!-- wp:group {\"layout\":{\"inherit\":false}} -->\n<div class=\"wp-block-group\"></div>\n<!-- /wp:group --></div>\n<!-- /wp:group -->\n\n<!-- wp:cover {\"url\":\"http://raw.githubusercontent.com/ellatrix/block-themes-directory/main/themes/edunation/images/default-image-banner.jpg\",\"id\":415,\"dimRatio\":0,\"focalPoint\":{\"x\":\"0.51\",\"y\":\"0.53\"},\"minHeight\":300,\"customGradient\":\"linear-gradient(90deg,rgb(0,0,0) 30%,rgba(150,149,240,0) 96%)\",\"isDark\":false,\"align\":\"full\"} -->\n<div class=\"wp-block-cover alignfull is-light\" style=\"min-height:300px\"><span aria-hidden=\"true\" class=\"wp-block-cover__background has-background-dim-0 has-background-dim has-background-gradient\" style=\"background:linear-gradient(90deg,rgb(0,0,0) 30%,rgba(150,149,240,0) 96%)\"></span><img class=\"wp-block-cover__image-background wp-image-415\" alt=\"\" src=\"http://raw.githubusercontent.com/ellatrix/block-themes-directory/main/themes/edunation/images/default-image-banner.jpg\" style=\"object-position:51% 53%\" data-object-fit=\"cover\" data-object-position=\"51% 53%\"/><div class=\"wp-block-cover__inner-container\"><!-- wp:group {\"align\":\"wide\",\"layout\":{\"inherit\":true}} -->\n<div class=\"wp-block-group alignwide\"><!-- wp:post-title {\"textAlign\":\"center\",\"level\":1,\"align\":\"wide\",\"textColor\":\"foreground\",\"fontSize\":\"medium\"} /--></div>\n<!-- /wp:group --></div></div>\n<!-- /wp:cover -->\nWarning: Trying to access array offset on value of type int in /Applications/MAMP/htdocs/block-based-themes/pattern.php on line 15\n\r\n\r\n<!-- wp:group {\"tagName\":\"main\",\"align\":\"full\",\"style\":{\"spacing\":{\"padding\":{\"top\":\"80px\",\"bottom\":\"80px\",\"left\":\"20px\",\"right\":\"20px\"}}},\"className\":\"no-margin no-padding\",\"layout\":{\"inherit\":true}} -->\r\n<main class=\"wp-block-group alignfull no-margin no-padding\" style=\"padding-top:80px;padding-right:20px;padding-bottom:80px;padding-left:20px\"><!-- wp:columns {\"align\":\"wide\"} -->\r\n\t<div class=\"wp-block-columns alignwide\"><!-- wp:column {\"width\":\"25%\"} -->\r\n\t<div class=\"wp-block-column\" style=\"flex-basis:25%\"><!-- wp:group -->\r\n\t<div class=\"wp-block-group\"><!-- wp:group {\"style\":{\"spacing\":{\"padding\":{\"top\":\"0px\",\"right\":\"0px\",\"bottom\":\"0px\",\"left\":\"0px\"}}}} -->\r\n\t<div class=\"wp-block-group\" style=\"padding-top:0px;padding-right:0px;padding-bottom:0px;padding-left:0px\"><!-- wp:group {\"style\":{\"spacing\":{\"blockGap\":\"5px\"}},\"className\":\"has-no-hover-shadow-dark animated animated-fadeInUp\"} -->\r\n\t<div class=\"wp-block-group has-no-hover-shadow-dark animated animated-fadeInUp\"><!-- wp:group {\"style\":{\"spacing\":{\"padding\":{\"top\":\"30px\",\"right\":\"30px\",\"bottom\":\"30px\",\"left\":\"30px\"}}},\"backgroundColor\":\"white\"} -->\r\n\t<div class=\"wp-block-group has-white-background-color has-background\" style=\"padding-top:30px;padding-right:30px;padding-bottom:30px;padding-left:30px\"><!-- wp:search {\"label\":\"\",\"showLabel\":false,\"placeholder\":\" Search\",\"width\":100,\"widthUnit\":\"%\",\"buttonText\":\"Search\",\"buttonUseIcon\":true,\"style\":{\"border\":{\"radius\":\"0px\",\"width\":\"0px\",\"style\":\"none\"}},\"backgroundColor\":\"primary\",\"textColor\":\"light\"} /--></div>\r\n\t<!-- /wp:group --></div>\r\n\t<!-- /wp:group -->\r\n\t\r\n\t<!-- wp:group {\"style\":{\"spacing\":{\"padding\":{\"top\":\"15px\",\"right\":\"15px\",\"bottom\":\"15px\",\"left\":\"15px\"},\"blockGap\":\"0px\"}},\"backgroundColor\":\"white\",\"className\":\"has-no-hover-shadow-dark animated animated-fadeInUp\"} -->\r\n\t<div class=\"wp-block-group has-no-hover-shadow-dark animated animated-fadeInUp has-white-background-color has-background\" style=\"padding-top:15px;padding-right:15px;padding-bottom:15px;padding-left:15px\"><!-- wp:group {\"style\":{\"spacing\":{\"padding\":{\"top\":\"10px\",\"right\":\"10px\",\"bottom\":\"0px\",\"left\":\"20px\"},\"blockGap\":\"10px\",\"margin\":{\"top\":\"0px\",\"bottom\":\"0px\"}}},\"backgroundColor\":\"white\",\"layout\":{\"inherit\":true}} -->\r\n\t<div class=\"wp-block-group has-white-background-color has-background\" style=\"margin-top:0px;margin-bottom:0px;padding-top:10px;padding-right:10px;padding-bottom:0px;padding-left:20px\"><!-- wp:heading {\"level\":3,\"align\":\"wide\",\"style\":{\"spacing\":{\"margin\":{\"top\":\"0px\",\"right\":\"0px\",\"bottom\":\"0px\",\"left\":\"0px\"}}},\"textColor\":\"background\"} -->\r\n\t<h3 class=\"alignwide has-background-color has-text-color\" style=\"margin-top:0px;margin-right:0px;margin-bottom:0px;margin-left:0px\">\r\n\t\t\t\t\tArchive\t\t\t</h3>\r\n\t<!-- /wp:heading -->\r\n\t\r\n\t<!-- wp:group {\"align\":\"wide\",\"layout\":{\"inherit\":false}} -->\r\n\t<div class=\"wp-block-group alignwide\"><!-- wp:separator {\"backgroundColor\":\"primary\",\"className\":\"is-style-wide\"} -->\r\n\t<hr class=\"wp-block-separator has-text-color has-primary-color has-alpha-channel-opacity has-primary-background-color has-background is-style-wide\"/>\r\n\t<!-- /wp:separator --></div>\r\n\t<!-- /wp:group --></div>\r\n\t<!-- /wp:group -->\r\n\t\r\n\t<!-- wp:group {\"style\":{\"spacing\":{\"padding\":{\"top\":\"10px\",\"right\":\"20px\",\"bottom\":\"10px\",\"left\":\"20px\"}}}} -->\r\n\t<div class=\"wp-block-group\" style=\"padding-top:10px;padding-right:20px;padding-bottom:10px;padding-left:20px\"><!-- wp:archives /--></div>\r\n\t<!-- /wp:group --></div>\r\n\t<!-- /wp:group -->\r\n\t\r\n\t<!-- wp:group {\"style\":{\"spacing\":{\"padding\":{\"top\":\"15px\",\"right\":\"15px\",\"bottom\":\"15px\",\"left\":\"15px\"},\"blockGap\":\"0px\"}},\"backgroundColor\":\"white\",\"className\":\"has-no-hover-shadow-dark animated animated-fadeInUp\"} -->\r\n\t<div class=\"wp-block-group has-no-hover-shadow-dark animated animated-fadeInUp has-white-background-color has-background\" style=\"padding-top:15px;padding-right:15px;padding-bottom:15px;padding-left:15px\"><!-- wp:group {\"style\":{\"spacing\":{\"padding\":{\"top\":\"10px\",\"right\":\"10px\",\"bottom\":\"0px\",\"left\":\"20px\"},\"blockGap\":\"10px\",\"margin\":{\"top\":\"0px\",\"bottom\":\"0px\"}}},\"backgroundColor\":\"white\",\"layout\":{\"inherit\":true}} -->\r\n\t<div class=\"wp-block-group has-white-background-color has-background\" style=\"margin-top:0px;margin-bottom:0px;padding-top:10px;padding-right:10px;padding-bottom:0px;padding-left:20px\"><!-- wp:heading {\"level\":3,\"align\":\"wide\",\"style\":{\"spacing\":{\"margin\":{\"top\":\"0px\",\"right\":\"0px\",\"bottom\":\"0px\",\"left\":\"0px\"}}},\"textColor\":\"background\"} -->\r\n\t<h3 class=\"alignwide has-background-color has-text-color\" style=\"margin-top:0px;margin-right:0px;margin-bottom:0px;margin-left:0px\">\r\n\t\t\t\t\tCategorise\t\t\t</h3>\r\n\t<!-- /wp:heading -->\r\n\t\r\n\t<!-- wp:group {\"align\":\"wide\",\"layout\":{\"inherit\":false}} -->\r\n\t<div class=\"wp-block-group alignwide\"><!-- wp:separator {\"backgroundColor\":\"primary\",\"className\":\"is-style-wide\"} -->\r\n\t<hr class=\"wp-block-separator has-text-color has-primary-color has-alpha-channel-opacity has-primary-background-color has-background is-style-wide\"/>\r\n\t<!-- /wp:separator --></div>\r\n\t<!-- /wp:group --></div>\r\n\t<!-- /wp:group -->\r\n\t\r\n\t<!-- wp:group {\"style\":{\"spacing\":{\"padding\":{\"top\":\"30px\",\"right\":\"30px\",\"bottom\":\"30px\",\"left\":\"30px\"}}}} -->\r\n\t<div class=\"wp-block-group\" style=\"padding-top:30px;padding-right:30px;padding-bottom:30px;padding-left:30px\"><!-- wp:categories /--></div>\r\n\t<!-- /wp:group --></div>\r\n\t<!-- /wp:group -->\r\n\t\r\n\t<!-- wp:group {\"style\":{\"spacing\":{\"padding\":{\"top\":\"15px\",\"right\":\"15px\",\"bottom\":\"15px\",\"left\":\"15px\"},\"blockGap\":\"0px\"}},\"backgroundColor\":\"white\",\"className\":\"has-no-hover-shadow-dark animated animated-fadeInUp\"} -->\r\n\t<div class=\"wp-block-group has-no-hover-shadow-dark animated animated-fadeInUp has-white-background-color has-background\" style=\"padding-top:15px;padding-right:15px;padding-bottom:15px;padding-left:15px\"><!-- wp:group {\"style\":{\"spacing\":{\"padding\":{\"top\":\"10px\",\"right\":\"10px\",\"bottom\":\"0px\",\"left\":\"20px\"},\"blockGap\":\"10px\",\"margin\":{\"top\":\"0px\",\"bottom\":\"0px\"}}},\"backgroundColor\":\"white\",\"layout\":{\"inherit\":true}} -->\r\n\t<div class=\"wp-block-group has-white-background-color has-background\" style=\"margin-top:0px;margin-bottom:0px;padding-top:10px;padding-right:10px;padding-bottom:0px;padding-left:20px\"><!-- wp:heading {\"level\":3,\"align\":\"wide\",\"style\":{\"spacing\":{\"margin\":{\"top\":\"0px\",\"right\":\"0px\",\"bottom\":\"0px\",\"left\":\"0px\"}}},\"textColor\":\"background\"} -->\r\n\t<h3 class=\"alignwide has-background-color has-text-color\" style=\"margin-top:0px;margin-right:0px;margin-bottom:0px;margin-left:0px\">\r\n\t\t\t\t\tRecent Posts\t\t\t</h3>\r\n\t<!-- /wp:heading -->\r\n\t\r\n\t<!-- wp:group {\"align\":\"wide\",\"layout\":{\"inherit\":false}} -->\r\n\t<div class=\"wp-block-group alignwide\"><!-- wp:separator {\"backgroundColor\":\"primary\",\"className\":\"is-style-wide\"} -->\r\n\t<hr class=\"wp-block-separator has-text-color has-primary-color has-alpha-channel-opacity has-primary-background-color has-background is-style-wide\"/>\r\n\t<!-- /wp:separator --></div>\r\n\t<!-- /wp:group --></div>\r\n\t<!-- /wp:group -->\r\n\t\r\n\t<!-- wp:group {\"style\":{\"spacing\":{\"padding\":{\"top\":\"30px\",\"right\":\"30px\",\"bottom\":\"30px\",\"left\":\"30px\"}}}} -->\r\n\t<div class=\"wp-block-group\" style=\"padding-top:30px;padding-right:30px;padding-bottom:30px;padding-left:30px\"><!-- wp:latest-posts {\"displayPostDate\":true,\"displayFeaturedImage\":true,\"featuredImageAlign\":\"left\",\"featuredImageSizeWidth\":75,\"featuredImageSizeHeight\":75} /--></div>\r\n\t<!-- /wp:group --></div>\r\n\t<!-- /wp:group -->\r\n\t\r\n\t<!-- wp:group {\"style\":{\"spacing\":{\"padding\":{\"top\":\"15px\",\"right\":\"15px\",\"bottom\":\"15px\",\"left\":\"15px\"},\"blockGap\":\"0px\"}},\"backgroundColor\":\"white\",\"className\":\"has-no-hover-shadow-dark animated animated-fadeInUp\"} -->\r\n\t<div class=\"wp-block-group has-no-hover-shadow-dark animated animated-fadeInUp has-white-background-color has-background\" style=\"padding-top:15px;padding-right:15px;padding-bottom:15px;padding-left:15px\"><!-- wp:group {\"style\":{\"spacing\":{\"padding\":{\"top\":\"10px\",\"right\":\"10px\",\"bottom\":\"0px\",\"left\":\"20px\"},\"blockGap\":\"10px\",\"margin\":{\"top\":\"0px\",\"bottom\":\"0px\"}}},\"backgroundColor\":\"white\",\"layout\":{\"inherit\":true}} -->\r\n\t<div class=\"wp-block-group has-white-background-color has-background\" style=\"margin-top:0px;margin-bottom:0px;padding-top:10px;padding-right:10px;padding-bottom:0px;padding-left:20px\"><!-- wp:heading {\"level\":3,\"align\":\"wide\",\"style\":{\"spacing\":{\"margin\":{\"top\":\"0px\",\"right\":\"0px\",\"bottom\":\"0px\",\"left\":\"0px\"}}},\"textColor\":\"background\"} -->\r\n\t<h3 class=\"alignwide has-background-color has-text-color\" style=\"margin-top:0px;margin-right:0px;margin-bottom:0px;margin-left:0px\">\r\n\t\t\t\t\tTags\t\t\t</h3>\r\n\t<!-- /wp:heading -->\r\n\t\r\n\t<!-- wp:group {\"align\":\"wide\",\"layout\":{\"inherit\":false}} -->\r\n\t<div class=\"wp-block-group alignwide\"><!-- wp:separator {\"backgroundColor\":\"primary\",\"className\":\"is-style-wide\"} -->\r\n\t<hr class=\"wp-block-separator has-text-color has-primary-color has-alpha-channel-opacity has-primary-background-color has-background is-style-wide\"/>\r\n\t<!-- /wp:separator --></div>\r\n\t<!-- /wp:group --></div>\r\n\t<!-- /wp:group -->\r\n\t\r\n\t<!-- wp:group {\"style\":{\"spacing\":{\"padding\":{\"top\":\"30px\",\"right\":\"30px\",\"bottom\":\"30px\",\"left\":\"30px\"}}}} -->\r\n\t<div class=\"wp-block-group\" style=\"padding-top:30px;padding-right:30px;padding-bottom:30px;padding-left:30px\"><!-- wp:tag-cloud /--></div>\r\n\t<!-- /wp:group --></div>\r\n\t<!-- /wp:group -->\r\n\t\r\n\t<!-- wp:group {\"style\":{\"spacing\":{\"padding\":{\"top\":\"15px\",\"right\":\"15px\",\"bottom\":\"15px\",\"left\":\"15px\"},\"blockGap\":\"0px\"}},\"backgroundColor\":\"white\",\"className\":\"has-no-hover-shadow-dark animated animated-fadeInUp\"} -->\r\n\t<div class=\"wp-block-group has-no-hover-shadow-dark animated animated-fadeInUp has-white-background-color has-background\" style=\"padding-top:15px;padding-right:15px;padding-bottom:15px;padding-left:15px\"><!-- wp:group {\"style\":{\"spacing\":{\"padding\":{\"top\":\"10px\",\"right\":\"10px\",\"bottom\":\"0px\",\"left\":\"20px\"},\"blockGap\":\"10px\",\"margin\":{\"top\":\"0px\",\"bottom\":\"0px\"}}},\"backgroundColor\":\"white\",\"layout\":{\"inherit\":true}} -->\r\n\t<div class=\"wp-block-group has-white-background-color has-background\" style=\"margin-top:0px;margin-bottom:0px;padding-top:10px;padding-right:10px;padding-bottom:0px;padding-left:20px\"><!-- wp:heading {\"level\":3,\"align\":\"wide\",\"style\":{\"spacing\":{\"margin\":{\"top\":\"0px\",\"right\":\"0px\",\"bottom\":\"0px\",\"left\":\"0px\"}}},\"textColor\":\"background\"} -->\r\n\t<h3 class=\"alignwide has-background-color has-text-color\" style=\"margin-top:0px;margin-right:0px;margin-bottom:0px;margin-left:0px\">\r\n\t\t\t\t\tSocial Links\t\t\t</h3>\r\n\t<!-- /wp:heading -->\r\n\t\r\n\t<!-- wp:group {\"align\":\"wide\",\"layout\":{\"inherit\":false}} -->\r\n\t<div class=\"wp-block-group alignwide\"><!-- wp:separator {\"backgroundColor\":\"primary\",\"className\":\"is-style-wide\"} -->\r\n\t<hr class=\"wp-block-separator has-text-color has-primary-color has-alpha-channel-opacity has-primary-background-color has-background is-style-wide\"/>\r\n\t<!-- /wp:separator --></div>\r\n\t<!-- /wp:group --></div>\r\n\t<!-- /wp:group -->\r\n\t\r\n\t<!-- wp:group {\"style\":{\"spacing\":{\"padding\":{\"top\":\"30px\",\"right\":\"30px\",\"bottom\":\"30px\",\"left\":\"30px\"}}}} -->\r\n\t<div class=\"wp-block-group\" style=\"padding-top:30px;padding-right:30px;padding-bottom:30px;padding-left:30px\"><!-- wp:social-links {\"iconColor\":\"background\",\"iconColorValue\":\"#ffffff\",\"openInNewTab\":true,\"size\":\"has-small-icon-size\",\"className\":\"is-style-default\",\"layout\":{\"type\":\"flex\",\"justifyContent\":\"left\"},\"style\":{\"spacing\":{\"blockGap\":\"20px\"}}} -->\r\n\t<ul class=\"wp-block-social-links has-small-icon-size has-icon-color is-style-default\"><!-- wp:social-link {\"url\":\"#\",\"service\":\"facebook\"} /-->\r\n\t\r\n\t<!-- wp:social-link {\"url\":\"#\",\"service\":\"twitter\"} /-->\r\n\t\r\n\t<!-- wp:social-link {\"url\":\"#\",\"service\":\"linkedin\"} /-->\r\n\t\r\n\t<!-- wp:social-link {\"url\":\"#\",\"service\":\"instagram\"} /--></ul>\r\n\t<!-- /wp:social-links --></div>\r\n\t<!-- /wp:group --></div>\r\n\t<!-- /wp:group --></div>\r\n\t<!-- /wp:group --></div>\r\n\t<!-- /wp:group --></div>\r\n\t<!-- /wp:column -->\r\n\t\r\n\t<!-- wp:column -->\r\n\t<div class=\"wp-block-column\"></div>\r\n\t<!-- /wp:column -->\r\n\t\r\n\t<!-- wp:column {\"width\":\"75%\",\"style\":{\"spacing\":{\"padding\":{\"top\":\"0px\",\"right\":\"0px\",\"bottom\":\"0px\",\"left\":\"0px\"}}}} -->\r\n\t<div class=\"wp-block-column\" style=\"padding-top:0px;padding-right:0px;padding-bottom:0px;padding-left:0px;flex-basis:75%\"><!-- wp:group {\"tagName\":\"main\",\"style\":{\"spacing\":{\"padding\":{\"top\":\"0px\",\"bottom\":\"40px\"}}},\"layout\":{\"inherit\":true}} -->\r\n\t<main class=\"wp-block-group\" style=\"padding-top:0px;padding-bottom:40px\"><!-- wp:post-featured-image {\"align\":\"full\"} /-->\r\n\t\r\n\t<!-- wp:post-title {\"textAlign\":\"left\",\"level\":1,\"align\":\"full\",\"textColor\":\"foreground\"} /-->\r\n\t\r\n\t<!-- wp:post-content {\"align\":\"full\"} /--></main>\r\n\t<!-- /wp:group --></div>\r\n\t<!-- /wp:column --></div>\r\n\t<!-- /wp:columns --></main>\r\n\t<!-- /wp:group -->\r\n\t\r\n<!-- wp:template-part {\"slug\":\"footer\",\"tagName\":\"footer\"} /-->"},{"title":"Gutenify University","html":"<!-- wp:template-part {\"slug\":\"header\",\"tagName\":\"header\"} /-->\n\n<!-- wp:group {\"tagName\":\"main\",\"align\":\"full\",\"className\":\"no-margin no-padding\",\"layout\":{\"inherit\":true}} -->\n<main class=\"wp-block-group alignfull no-margin no-padding\">\n\t<!-- wp:group {\"align\":\"full\",\"layout\":{\"inherit\":true}} -->\n<div class=\"wp-block-group alignfull\">\n\t<!-- wp:cover {\"url\":\"http://raw.githubusercontent.com/ellatrix/block-themes-directory/main/themes/gutenify-university/images/single-header.png\",\"dimRatio\":50,\"overlayColor\":\"foreground\",\"focalPoint\":{\"x\":\"0.59\",\"y\":\"0.45\"},\"minHeight\":300,\"minHeightUnit\":\"px\",\"contentPosition\":\"center center\",\"isDark\":false,\"align\":\"full\"} -->\n\t<div class=\"wp-block-cover alignfull is-light\" style=\"min-height:300px\"><span aria-hidden=\"true\"\n\t\t\tclass=\"wp-block-cover__background has-foreground-background-color has-background-dim\"></span><img\n\t\t\tclass=\"wp-block-cover__image-background\" alt=\"\"\n\t\t\tsrc=\"http://raw.githubusercontent.com/ellatrix/block-themes-directory/main/themes/gutenify-university/images/single-header.png\"\n\t\t\tstyle=\"object-position:59% 45%\" data-object-fit=\"cover\" data-object-position=\"59% 45%\" />\n\t\t<div class=\"wp-block-cover__inner-container\">\n\t\t\t<!-- wp:post-title {\"textAlign\":\"center\",\"level\":1,\"align\":\"wide\",\"style\":{\"spacing\":{\"margin\":{\"bottom\":\"0px\",\"top\":\"0px\"}}},\"textColor\":\"background\",\"fontSize\":\"large\"} /-->\n\t\t</div>\n\t</div>\n\t<!-- /wp:cover -->\n\n\t<!-- wp:post-featured-image {\"align\":\"wide\",\"style\":{\"spacing\":{\"margin\":{\"bottom\":\"var(--wp--custom--spacing--medium, 6rem)\"}}}} /-->\n</div>\n<!-- /wp:group -->\n\nWarning: Trying to access array offset on value of type int in /Applications/MAMP/htdocs/block-based-themes/pattern.php on line 15\n\n\n\t<!-- wp:spacer {\"height\":\"10px\"} -->\n\t<div style=\"height:10px\" aria-hidden=\"true\" class=\"wp-block-spacer\"></div>\n\t<!-- /wp:spacer -->\n\n\t<!-- wp:columns {\"align\":\"wide\"} -->\n\t<div class=\"wp-block-columns alignwide\">\n\t\t<!-- wp:column {\"width\":\"33.33%\"} -->\n\t\t<div class=\"wp-block-column\" style=\"flex-basis:33.33%\">\n\t\t\t<!-- wp:template-part {\"slug\":\"sidebar\",\"tagName\":\"div\"} /-->\n\t\t</div>\n\t\t<!-- /wp:column -->\n\n\t\t<!-- wp:column -->\n\t\t<div class=\"wp-block-column\">\n\t\t</div>\n\t\t<!-- /wp:column -->\n\n\t\t<!-- wp:column {\"width\":\"66.66%\",\"style\":{\"spacing\":{\"padding\":{\"top\":\"0px\",\"right\":\"0px\",\"bottom\":\"0px\",\"left\":\"0px\"}}}} -->\n\t\t<div class=\"wp-block-column\"\n\t\t\tstyle=\"padding-top:0px;padding-right:0px;padding-bottom:0px;padding-left:0px;flex-basis:66.66%\">\n\t\t\t<!-- wp:query {\"queryId\":1,\"query\":{\"perPage\":\"3\",\"pages\":\"\",\"offset\":\"\",\"postType\":\"post\",\"order\":\"desc\",\"orderBy\":\"date\",\"author\":\"\",\"search\":\"\",\"exclude\":[],\"sticky\":\"\",\"inherit\":false},\"tagName\":\"main\",\"displayLayout\":{\"type\":\"flex\",\"columns\":2},\"align\":\"wide\",\"layout\":{\"inherit\":true}} -->\n<main class=\"wp-block-query alignwide\">\n        <!-- wp:post-template {\"align\":\"wide\"} -->\n        <!-- wp:group {\"layout\":{\"inherit\":true}} -->\n        <div class=\"wp-block-group\">\n\n                <!-- wp:post-featured-image {\"isLink\":true,\"align\":\"wide\"} /-->\n                <!-- wp:columns {\"align\":\"wide\"} -->\n                <div class=\"wp-block-columns alignwide gutenify-university-post-content\">\n                        <!-- wp:column {\"width\":\"\"} -->\n                        <div class=\"wp-block-column\">\n                                <!-- wp:post-title {\"isLink\":true,\"align\":\"wide\",\"fontSize\":\"var(--wp--custom--typography--font-size--huge, clamp(2.25rem, 4vw, 2.75rem))\"} /-->\n                                <!-- wp:post-excerpt /-->\n\n                                <!-- wp:post-date {\"format\":\"F j, Y\",\"isLink\":true,\"style\":{\"typography\":{\"fontStyle\":\"italic\",\"fontWeight\":\"400\"}},\"fontSize\":\"small\"} /-->\n                        </div>\n                        <!-- /wp:column -->\n                </div>\n                <!-- /wp:columns -->\n\n        </div>\n        <!-- /wp:group -->\n        <!-- wp:spacer {\"height\":20} -->\n        <div style=\"height:20px\" aria-hidden=\"true\" class=\"wp-block-spacer\"></div>\n        <!-- /wp:spacer -->\n        <!-- /wp:post-template -->\n\n        <!-- wp:query-pagination {\"paginationArrow\":\"arrow\",\"align\":\"center\",\"layout\":{\"type\":\"flex\",\"justifyContent\":\"space-between\"}} -->\n        <!-- wp:query-pagination-previous {\"fontSize\":\"small\"} /-->\n\n        <!-- wp:query-pagination-numbers /-->\n\n        <!-- wp:query-pagination-next {\"fontSize\":\"small\"} /-->\n        <!-- /wp:query-pagination -->\n</main>\n<!-- /wp:query -->\n\nWarning: Trying to access array offset on value of type int in /Applications/MAMP/htdocs/block-based-themes/pattern.php on line 15\n\n\t\t</div>\n\t\t<!-- /wp:column -->\n\t</div>\n\t<!-- /wp:columns -->\n</main>\n<!-- /wp:group -->\n\n<!-- wp:template-part {\"slug\":\"footer\",\"tagName\":\"footer\"} /-->\n"}]