[{"title":"Raft","html":"<!-- wp:post-content {\"layout\":{\"inherit\":true}} /-->\n"},{"title":"Jaxon","html":"<!-- wp:post-content {\"layout\":{\"inherit\":true}} /-->\n"},{"title":"Fork","html":"<!-- wp:post-content {\"layout\":{\"inherit\":true}} /-->\n"},{"title":"Riverbank","html":"<!-- wp:post-content {\"layout\":{\"inherit\":true}} /-->\n"},{"title":"Björk","html":"<!-- wp:post-content {\"layout\":{\"inherit\":true}} /-->\n"},{"title":"Beaumont","html":"<!-- wp:post-content {\"layout\":{\"inherit\":true}} /-->\n"},{"title":"Poe","html":"<!-- wp:post-content {\"layout\":{\"inherit\":true}} /-->\n"},{"title":"Molten","html":"<!-- wp:post-content {\"layout\":{\"inherit\":true}} /-->\n"},{"title":"Cormorant","html":"<!-- wp:post-content {\"layout\":{\"inherit\":true}} /-->"}]